.gitignore
CHANGES.txt
CONTRIBUTORS.txt
MANIFEST.in
README.txt
bootstrap.py
buildout.cfg
setup.cfg
setup.py
docs/LICENSE.GPL
docs/LICENSE.txt
src/edition1/__init__.py
src/edition1.menu.egg-info/PKG-INFO
src/edition1.menu.egg-info/SOURCES.txt
src/edition1.menu.egg-info/dependency_links.txt
src/edition1.menu.egg-info/entry_points.txt
src/edition1.menu.egg-info/namespace_packages.txt
src/edition1.menu.egg-info/not-zip-safe
src/edition1.menu.egg-info/paster_plugins.txt
src/edition1.menu.egg-info/requires.txt
src/edition1.menu.egg-info/top_level.txt
src/edition1/menu/__init__.py
src/edition1/menu/build_i18n.sh
src/edition1/menu/configure.zcml
src/edition1/menu/interfaces.py
src/edition1/menu/permissions.zcml
src/edition1/menu/profiles.zcml
src/edition1/menu/testing.py
src/edition1/menu/testing.zcml
src/edition1/menu/upgradesteps.py
src/edition1/menu/browser/__init__.py
src/edition1/menu/browser/configure.zcml
src/edition1/menu/browser/controlpanel.py
src/edition1/menu/browser/resources/icon.png
src/edition1/menu/browser/resources/menu.css
src/edition1/menu/browser/resources/responsive-menu.js
src/edition1/menu/locales/edition1.menu.pot
src/edition1/menu/locales/en/LC_MESSAGES/edition1.menu.po
src/edition1/menu/locales/nl/LC_MESSAGES/edition1.menu.po
src/edition1/menu/profiles/default/controlpanel.xml
src/edition1/menu/profiles/default/cssregistry.xml
src/edition1/menu/profiles/default/jsregistry.xml
src/edition1/menu/profiles/default/metadata.xml
src/edition1/menu/profiles/default/registry.xml
src/edition1/menu/profiles/default/rolemap.xml
src/edition1/menu/profiles/testing/metadata.xml
src/edition1/menu/tests/__init__.py
src/edition1/menu/tests/test_example.py
src/edition1/menu/viewlets/__init__.py
src/edition1/menu/viewlets/configure.zcml
src/edition1/menu/viewlets/menu.pt
src/edition1/menu/viewlets/menu.py
src/edition1/menu/viewlets/menu_recurse.pt