Metadata-Version: 1.0
Name: edition1.menu
Version: 0.1a6
Summary: A responsive menu for Plone themes.
Home-page: https://github.com/edition1/edition1.menu
Author: Edition1
Author-email: info@edition1.nl
License: gpl
Platform: UNKNOWN
Classifier: Environment :: Web Environment
Classifier: Framework :: Plone
Classifier: Operating System :: OS Independent
Classifier: Programming Language :: Python
Classifier: Programming Language :: Python :: 2.6
Classifier: Topic :: Software Development :: Libraries :: Python Modules
